Workbook

Sheet Leeswijzer
A1: OpdrachtZeker — financieel model (12 maanden)
A3: Strategie: eerst GRATIS BETA, daarna abonnementen zodra er betalende mensen zijn.
A5: Hoe werkt dit model?
A7: 1. Blad 'Aannames' is de ENIGE plek waar je invoer wijzigt (gele cellen).
A8: - 'Laatste gratis beta-maand': tot en met deze maand is het product gratis (geen omzet).
A9: - 'Groei-boost': gratis beta trekt sneller nieuwe klanten aan.
A10: 2. Blad 'Model' rekent 12 maanden door: klanten, MRR, kosten, resultaat en kaspositie.
A11: Alle maandcellen zijn formules en herberekenen automatisch in Excel/Sheets.
A12: 3. Blad 'Scenario' vergelijkt pessimistisch / base / optimistisch, inclusief
A13: eerste break-even maand en minimaal benodigd startkapitaal.
A14: 4. Blad 'Fasen' koppelt de modeluitkomsten aan de fasen uit het businessplan.
A16: Let op: maand 1 = start van de verkoop (na validatiefase). Alle bedragen in euro's.
... A18: Dit is een prognose- en beslissingsinstrument, geen garantie.

Sheet Aannames
A1: Aannames (base case) — gele cellen mag je aanpassen
A2: Parameter | B2: Waarde | C2: Eenheid | D2: Toelichting
A3: Startkapitaal | B3: 75000 | C3: EUR | D3: Eigen middelen + kleine lening
A4: Arpu | B4: 230 | C4: EUR/mnd | D4: Gemiddeld abonnement opdrachtgever (mix 60% x 149 / 30% x 299 / 10% x 499)
A5: Pro prijs | B5: 12 | C5: EUR/mnd | D5: ZZP Pro-abonnement
A6: Conversie pro | B6: 0.04 | C6: % | D6: Van nieuwe gratis ZZP-leden naar betalend Pro
A7: Churn | B7: 0.03 | C7: %/mnd | D7: Maandelijkse churn opdrachtgevers
A8: Churn pro | B8: 0.02 | C8: %/mnd | D8: Maandelijkse churn ZZP Pro
A9: Cac | B9: 600 | C9: EUR | D9: Acquisitiekosten per opdrachtgever (marketing)
A10: Sales new | B10: 2 | C10: per mnd | D10: Nieuwe opdrachtgevers via directe sales (vanaf mnd 7)
A11: Commissie | B11: 15 | C11: EUR/mnd | D11: Commissie-inkomsten per actieve opdrachtgever (vanaf mnd 4)
A12: Salaris | B12: 5000 | C12: EUR/mnd | D12: Oprichtersalaris 2 x 2.500 (bootstrapped)
A13: Sales hire | B13: 4500 | C13: EUR/mnd | D13: Sales-hire (vanaf mnd 7)
A14: Cloud | B14: 500 | C14: EUR/mnd | D14: Cloud/AI basiskosten
... A23: Beta boost | B23: 1.5 | C23: x | D23: Groei-boost nieuwe klanten tijdens gratis beta

Sheet Model
A1: Model — 12 maanden (maand 1 = start verkoop; maand 1 t/m beta = gratis)
B2: Formules op basis van blad Aannames
A3: Maand | C3: 1 | D3: 2 | E3: 3 | F3: 4 | G3: 5 | H3: 6 | I3: 7 | J3: 8 | K3: 9 | L3: 10 | M3: 11 | N3: 12
A4: Beta-fase? (1 = gratis, 0 = betaald) | C4: =IF(C$3<=Aannames!$B$22,1,0) | D4: =IF(D$3<=Aannames!$B$22,1,0) | E4: =IF(E$3<=Aannames!$B$22,1,0) | F4: =IF(F$3<=Aannames!$B$22,1,0) | G4: =IF(G$3<=Aannames!$B$22,1,0) | H4: =IF(H$3<=Aannames!$B$22,1,0) | I4: =IF(I$3<=Aannames!$B$22,1,0) | J4: =IF(J$3<=Aannames!$B$22,1,0) | ... N4: =IF(N$3<=Aannames!$B$22,1,0)
A5: INPUT Marketingbudget | C5: =IF(C$3<=3,Aannames!$B$18,IF(C$3<=6,Aannames!$B$19,Aannames!$B$20)) | D5: =IF(D$3<=3,Aannames!$B$18,IF(D$3<=6,Aannames!$B$19,Aannames!$B$20)) | E5: =IF(E$3<=3,Aannames!$B$18,IF(E$3<=6,Aannames!$B$19,Aannames!$B$20)) | F5: =IF(F$3<=3,Aannames!$B$18,IF(F$3<=6,Aannames!$B$19,Aannames!$B$20)) | G5: =IF(G$3<=3,Aannames!$B$18,IF(G$3<=6,Aannames!$B$19,Aannames!$B$20)) | H5: =IF(H$3<=3,Aannames!$B$18,IF(H$3<=6,Aannames!$B$19,Aannames!$B$20)) | I5: =IF(I$3<=3,Aannames!$B$18,IF(I$3<=6,Aannames!$B$19,Aannames!$B$20)) | J5: =IF(J$3<=3,Aannames!$B$18,IF(J$3<=6,Aannames!$B$19,Aannames!$B$20)) | ... N5: =IF(N$3<=3,Aannames!$B$18,IF(N$3<=6,Aannames!$B$19,Aannames!$B$20))
A6: INPUT Nieuwe gratis ZZP-leden | C6: 50 | D6: 70 | E6: 90 | F6: 110 | G6: 140 | H6: 170 | I6: 200 | J6: 240 | K6: 280 | L6: 320 | M6: 370 | N6: 420
A7: Nieuwe opdrachtgevers (marketing) | C7: =ROUND(C5/Aannames!$B$9*IF(C$3<=Aannames!$B$22,Aannames!$B$23,1),0) | D7: =ROUND(D5/Aannames!$B$9*IF(D$3<=Aannames!$B$22,Aannames!$B$23,1),0) | E7: =ROUND(E5/Aannames!$B$9*IF(E$3<=Aannames!$B$22,Aannames!$B$23,1),0) | F7: =ROUND(F5/Aannames!$B$9*IF(F$3<=Aannames!$B$22,Aannames!$B$23,1),0) | G7: =ROUND(G5/Aannames!$B$9*IF(G$3<=Aannames!$B$22,Aannames!$B$23,1),0) | H7: =ROUND(H5/Aannames!$B$9*IF(H$3<=Aannames!$B$22,Aannames!$B$23,1),0) | I7: =ROUND(I5/Aannames!$B$9*IF(I$3<=Aannames!$B$22,Aannames!$B$23,1),0) | J7: =ROUND(J5/Aannames!$B$9*IF(J$3<=Aannames!$B$22,Aannames!$B$23,1),0) | ... N7: =ROUND(N5/Aannames!$B$9*IF(N$3<=Aannames!$B$22,Aannames!$B$23,1),0)
A8: INPUT Nieuwe opdrachtgevers (directe sales) | C8: =IF(C$3>=7,Aannames!$B$10,0) | D8: =IF(D$3>=7,Aannames!$B$10,0) | E8: =IF(E$3>=7,Aannames!$B$10,0) | F8: =IF(F$3>=7,Aannames!$B$10,0) | G8: =IF(G$3>=7,Aannames!$B$10,0) | H8: =IF(H$3>=7,Aannames!$B$10,0) | I8: =IF(I$3>=7,Aannames!$B$10,0) | J8: =IF(J$3>=7,Aannames!$B$10,0) | ... N8: =IF(N$3>=7,Aannames!$B$10,0)
A9: Churn opdrachtgevers | C9: =IF(C$3=1,0,ROUND(B10*Aannames!$B$7,0)) | D9: =IF(D$3=1,0,ROUND(C10*Aannames!$B$7,0)) | E9: =IF(E$3=1,0,ROUND(D10*Aannames!$B$7,0)) | F9: =IF(F$3=1,0,ROUND(E10*Aannames!$B$7,0)) | G9: =IF(G$3=1,0,ROUND(F10*Aannames!$B$7,0)) | H9: =IF(H$3=1,0,ROUND(G10*Aannames!$B$7,0)) | I9: =IF(I$3=1,0,ROUND(H10*Aannames!$B$7,0)) | J9: =IF(J$3=1,0,ROUND(I10*Aannames!$B$7,0)) | ... N9: =IF(N$3=1,0,ROUND(M10*Aannames!$B$7,0))
A10: Actieve opdrachtgevers (eind) | C10: =C7+C8-C9 | D10: =C10+D7+D8-D9 | E10: =D10+E7+E8-E9 | F10: =E10+F7+F8-F9 | G10: =F10+G7+G8-G9 | H10: =G10+H7+H8-H9 | I10: =H10+I7+I8-I9 | J10: =I10+J7+J8-J9 | K10: =J10+K7+K8-K9 | ... N10: =M10+N7+N8-N9
A11: Cumulatief gratis ZZP-leden | C11: =C6 | D11: =C11+D6 | E11: =D11+E6 | F11: =E11+F6 | G11: =F11+G6 | H11: =G11+H6 | I11: =H11+I6 | J11: =I11+J6 | K11: =J11+K6 | ... N11: =M11+N6
A12: Nieuwe ZZP Pro | C12: =ROUND(C6*Aannames!$B$6,0) | D12: =ROUND(D6*Aannames!$B$6,0) | E12: =ROUND(E6*Aannames!$B$6,0) | F12: =ROUND(F6*Aannames!$B$6,0) | G12: =ROUND(G6*Aannames!$B$6,0) | H12: =ROUND(H6*Aannames!$B$6,0) | I12: =ROUND(I6*Aannames!$B$6,0) | J12: =ROUND(J6*Aannames!$B$6,0) | ... N12: =ROUND(N6*Aannames!$B$6,0)
A13: Churn ZZP Pro | C13: =IF(C$3=1,0,ROUND(B14*Aannames!$B$8,0)) | D13: =IF(D$3=1,0,ROUND(C14*Aannames!$B$8,0)) | E13: =IF(E$3=1,0,ROUND(D14*Aannames!$B$8,0)) | F13: =IF(F$3=1,0,ROUND(E14*Aannames!$B$8,0)) | G13: =IF(G$3=1,0,ROUND(F14*Aannames!$B$8,0)) | H13: =IF(H$3=1,0,ROUND(G14*Aannames!$B$8,0)) | I13: =IF(I$3=1,0,ROUND(H14*Aannames!$B$8,0)) | J13: =IF(J$3=1,0,ROUND(I14*Aannames!$B$8,0)) | ... N13: =IF(N$3=1,0,ROUND(M14*Aannames!$B$8,0))
A14: ZZP Pro abonnees (eind) | C14: =C12-C13 | D14: =C14+D12-D13 | E14: =D14+E12-E13 | F14: =E14+F12-F13 | G14: =F14+G12-G13 | H14: =G14+H12-H13 | I14: =H14+I12-I13 | J14: =I14+J12-J13 | K14: =J14+K12-K13 | ... N14: =M14+N12-N13
A15: MRR opdrachtgevers | C15: =C10*Aannames!$B$4*(1-C4) | D15: =D10*Aannames!$B$4*(1-D4) | E15: =E10*Aannames!$B$4*(1-E4) | F15: =F10*Aannames!$B$4*(1-F4) | G15: =G10*Aannames!$B$4*(1-G4) | H15: =H10*Aannames!$B$4*(1-H4) | I15: =I10*Aannames!$B$4*(1-I4) | J15: =J10*Aannames!$B$4*(1-J4) | ... N15: =N10*Aannames!$B$4*(1-N4)
A16: MRR ZZP Pro | C16: =C14*Aannames!$B$5*(1-C4) | D16: =D14*Aannames!$B$5*(1-D4) | E16: =E14*Aannames!$B$5*(1-E4) | F16: =F14*Aannames!$B$5*(1-F4) | G16: =G14*Aannames!$B$5*(1-G4) | H16: =H14*Aannames!$B$5*(1-H4) | I16: =I14*Aannames!$B$5*(1-I4) | J16: =J14*Aannames!$B$5*(1-J4) | ... N16: =N14*Aannames!$B$5*(1-N4)
A17: Commissie-inkomsten | C17: =IF(C$3>=4,C10*Aannames!$B$11*(1-C4),0) | D17: =IF(D$3>=4,D10*Aannames!$B$11*(1-D4),0) | E17: =IF(E$3>=4,E10*Aannames!$B$11*(1-E4),0) | F17: =IF(F$3>=4,F10*Aannames!$B$11*(1-F4),0) | G17: =IF(G$3>=4,G10*Aannames!$B$11*(1-G4),0) | H17: =IF(H$3>=4,H10*Aannames!$B$11*(1-H4),0) | I17: =IF(I$3>=4,I10*Aannames!$B$11*(1-I4),0) | J17: =IF(J$3>=4,J10*Aannames!$B$11*(1-J4),0) | ... N17: =IF(N$3>=4,N10*Aannames!$B$11*(1-N4),0)
A18: Totale omzet | C18: =C15+C16+C17 | D18: =D15+D16+D17 | E18: =E15+E16+E17 | F18: =F15+F16+F17 | G18: =G15+G16+G17 | H18: =H15+H16+H17 | I18: =I15+I16+I17 | J18: =J15+J16+J17 | ... N18: =N15+N16+N17
A19: Kosten personeel | C19: =Aannames!$B$12+IF(C$3>=7,Aannames!$B$13,0) | D19: =Aannames!$B$12+IF(D$3>=7,Aannames!$B$13,0) | E19: =Aannames!$B$12+IF(E$3>=7,Aannames!$B$13,0) | F19: =Aannames!$B$12+IF(F$3>=7,Aannames!$B$13,0) | G19: =Aannames!$B$12+IF(G$3>=7,Aannames!$B$13,0) | H19: =Aannames!$B$12+IF(H$3>=7,Aannames!$B$13,0) | I19: =Aannames!$B$12+IF(I$3>=7,Aannames!$B$13,0) | J19: =Aannames!$B$12+IF(J$3>=7,Aannames!$B$13,0) | ... N19: =Aannames!$B$12+IF(N$3>=7,Aannames!$B$13,0)
A20: Kosten marketing | C20: =C5 | D20: =D5 | E20: =E5 | F20: =F5 | G20: =G5 | H20: =H5 | I20: =I5 | J20: =J5 | ... N20: =N5
A21: Kosten techniek | C21: =Aannames!$B$14+C10*Aannames!$B$15 | D21: =Aannames!$B$14+D10*Aannames!$B$15 | E21: =Aannames!$B$14+E10*Aannames!$B$15 | F21: =Aannames!$B$14+F10*Aannames!$B$15 | G21: =Aannames!$B$14+G10*Aannames!$B$15 | H21: =Aannames!$B$14+H10*Aannames!$B$15 | I21: =Aannames!$B$14+I10*Aannames!$B$15 | J21: =Aannames!$B$14+J10*Aannames!$B$15 | ... N21: =Aannames!$B$14+N10*Aannames!$B$15
A22: Overige kosten | C22: =Aannames!$B$16+IF(C$3=2,Aannames!$B$17,0) | D22: =Aannames!$B$16+IF(D$3=2,Aannames!$B$17,0) | E22: =Aannames!$B$16+IF(E$3=2,Aannames!$B$17,0) | F22: =Aannames!$B$16+IF(F$3=2,Aannames!$B$17,0) | G22: =Aannames!$B$16+IF(G$3=2,Aannames!$B$17,0) | H22: =Aannames!$B$16+IF(H$3=2,Aannames!$B$17,0) | I22: =Aannames!$B$16+IF(I$3=2,Aannames!$B$17,0) | J22: =Aannames!$B$16+IF(J$3=2,Aannames!$B$17,0) | ... N22: =Aannames!$B$16+IF(N$3=2,Aannames!$B$17,0)
A23: Totale kosten | C23: =C19+C20+C21+C22 | D23: =D19+D20+D21+D22 | E23: =E19+E20+E21+E22 | F23: =F19+F20+F21+F22 | G23: =G19+G20+G21+G22 | H23: =H19+H20+H21+H22 | I23: =I19+I20+I21+I22 | J23: =J19+J20+J21+J22 | ... N23: =N19+N20+N21+N22
A24: Maandresultaat | C24: =C18-C23 | D24: =D18-D23 | E24: =E18-E23 | F24: =F18-F23 | G24: =G18-G23 | H24: =H18-H23 | I24: =I18-I23 | J24: =J18-J23 | ... N24: =N18-N23
A25: Kaspositie (eind) | C25: =Aannames!$B$3+C24 | D25: =C25+D24 | E25: =D25+E24 | F25: =E25+F24 | G25: =F25+G24 | H25: =G25+H24 | I25: =H25+I24 | J25: =I25+J24 | K25: =J25+K24 | ... N25: =M25+N24
A26: Kas zonder startkapitaal | C26: =C24 | D26: =C26+D24 | E26: =D26+E24 | F26: =E26+F24 | G26: =F26+G24 | H26: =G26+H24 | I26: =H26+I24 | J26: =I26+J24 | K26: =J26+K24 | ... N26: =M26+N24
A27: Runway-indicatie (mnd) | C27: =IF(C24>=0,"break-even",ROUND(C25/-C24,1)) | D27: =IF(D24>=0,"break-even",ROUND(D25/-D24,1)) | E27: =IF(E24>=0,"break-even",ROUND(E25/-E24,1)) | F27: =IF(F24>=0,"break-even",ROUND(F25/-F24,1)) | G27: =IF(G24>=0,"break-even",ROUND(G25/-G24,1)) | H27: =IF(H24>=0,"break-even",ROUND(H25/-H24,1)) | I27: =IF(I24>=0,"break-even",ROUND(I25/-I24,1)) | J27: =IF(J24>=0,"break-even",ROUND(J25/-J24,1)) | ... N27: =IF(N24>=0,"break-even",ROUND(N25/-N24,1))
A28: CAC gerealiseerd (marketing) | C28: =IFERROR(ROUND(C5/(C7+C8),0),0) | D28: =IFERROR(ROUND(D5/(D7+D8),0),0) | E28: =IFERROR(ROUND(E5/(E7+E8),0),0) | F28: =IFERROR(ROUND(F5/(F7+F8),0),0) | G28: =IFERROR(ROUND(G5/(G7+G8),0),0) | H28: =IFERROR(ROUND(H5/(H7+H8),0),0) | I28: =IFERROR(ROUND(I5/(I7+I8),0),0) | J28: =IFERROR(ROUND(J5/(J7+J8),0),0) | ... N28: =IFERROR(ROUND(N5/(N7+N8),0),0)
A29: LTV opdrachtgever | C29: =ROUND(Aannames!$B$4*(1/Aannames!$B$7)*Aannames!$B$21,0) | D29: =ROUND(Aannames!$B$4*(1/Aannames!$B$7)*Aannames!$B$21,0) | E29: =ROUND(Aannames!$B$4*(1/Aannames!$B$7)*Aannames!$B$21,0) | F29: =ROUND(Aannames!$B$4*(1/Aannames!$B$7)*Aannames!$B$21,0) | G29: =ROUND(Aannames!$B$4*(1/Aannames!$B$7)*Aannames!$B$21,0) | H29: =ROUND(Aannames!$B$4*(1/Aannames!$B$7)*Aannames!$B$21,0) | I29: =ROUND(Aannames!$B$4*(1/Aannames!$B$7)*Aannames!$B$21,0) | J29: =ROUND(Aannames!$B$4*(1/Aannames!$B$7)*Aannames!$B$21,0) | ... N29: =ROUND(Aannames!$B$4*(1/Aannames!$B$7)*Aannames!$B$21,0)
A30: LTV / CAC | C30: =IFERROR(ROUND(C29/C28,1),0) | D30: =IFERROR(ROUND(D29/D28,1),0) | E30: =IFERROR(ROUND(E29/E28,1),0) | F30: =IFERROR(ROUND(F29/F28,1),0) | G30: =IFERROR(ROUND(G29/G28,1),0) | H30: =IFERROR(ROUND(H29/H28,1),0) | I30: =IFERROR(ROUND(I29/I28,1),0) | J30: =IFERROR(ROUND(J29/J28,1),0) | ... N30: =IFERROR(ROUND(N29/N28,1),0)
A31: Positief resultaat? (1/0) | C31: =IF(C24>=0,1,0) | D31: =IF(D24>=0,1,0) | E31: =IF(E24>=0,1,0) | F31: =IF(F24>=0,1,0) | G31: =IF(G24>=0,1,0) | H31: =IF(H24>=0,1,0) | I31: =IF(I24>=0,1,0) | J31: =IF(J24>=0,1,0) | ... N31: =IF(N24>=0,1,0)
A33: Samenvatting
A34: Omzet na 12 maanden | B34: =N18
A35: Eerste maand met positief resultaat | B35: =IFERROR(MATCH(1,C31:N31,0),"geen binnen 12 mnd")
A36: Kaspositie eind maand 12 | B36: =N25
A37: Dieptepunt kas (zonder startkapitaal) | B37: =MIN(C26:N26)
A38: Minimaal startkapitaal nodig (base) | B38: =MAX(0,-MIN(C26:N26))

Sheet Scenario
A1: Scenario's — zelfde logica, andere aannames
A2: Parameter | B2: Pessimistisch | C2: Base | D2: Optimistisch
A3: Maandelijkse churn opdrachtgevers | B3: 0.06 | C3: 0.03 | D3: 0.02
A4: CAC per opdrachtgever | B4: 1000 | C4: 600 | D4: 450
A5: Gemiddelde abonnementsprijs opdrachtgever | B5: 190 | C5: 230 | D5: 260
A8: Scenario: Pessimistisch
A9: Actieve opdrachtgevers | C9: =ROUND(Model!C$5/$B$4*IF(Model!C$3<=Aannames!$B$22,Aannames!$B$23,1),0)+Model!C$8 | D9: =C9+ROUND(Model!D$5/$B$4*IF(Model!D$3<=Aannames!$B$22,Aannames!$B$23,1),0)+Model!D$8-ROUND(C9*$B$3,0) | E9: =D9+ROUND(Model!E$5/$B$4*IF(Model!E$3<=Aannames!$B$22,Aannames!$B$23,1),0)+Model!E$8-ROUND(D9*$B$3,0) | F9: =E9+ROUND(Model!F$5/$B$4*IF(Model!F$3<=Aannames!$B$22,Aannames!$B$23,1),0)+Model!F$8-ROUND(E9*$B$3,0) | G9: =F9+ROUND(Model!G$5/$B$4*IF(Model!G$3<=Aannames!$B$22,Aannames!$B$23,1),0)+Model!G$8-ROUND(F9*$B$3,0) | H9: =G9+ROUND(Model!H$5/$B$4*IF(Model!H$3<=Aannames!$B$22,Aannames!$B$23,1),0)+Model!H$8-ROUND(G9*$B$3,0) | I9: =H9+ROUND(Model!I$5/$B$4*IF(Model!I$3<=Aannames!$B$22,Aannames!$B$23,1),0)+Model!I$8-ROUND(H9*$B$3,0) | J9: =I9+ROUND(Model!J$5/$B$4*IF(Model!J$3<=Aannames!$B$22,Aannames!$B$23,1),0)+Model!J$8-ROUND(I9*$B$3,0) | K9: =J9+ROUND(Model!K$5/$B$4*IF(Model!K$3<=Aannames!$B$22,Aannames!$B$23,1),0)+Model!K$8-ROUND(J9*$B$3,0) | ... N9: =M9+ROUND(Model!N$5/$B$4*IF(Model!N$3<=Aannames!$B$22,Aannames!$B$23,1),0)+Model!N$8-ROUND(M9*$B$3,0)
A10: Totale omzet | C10: =(C9*$B$5+IF(Model!C$3>=4,C9*Aannames!$B$11,0))*(1-Model!C$4)+Model!C$16 | D10: =(D9*$B$5+IF(Model!D$3>=4,D9*Aannames!$B$11,0))*(1-Model!D$4)+Model!D$16 | E10: =(E9*$B$5+IF(Model!E$3>=4,E9*Aannames!$B$11,0))*(1-Model!E$4)+Model!E$16 | F10: =(F9*$B$5+IF(Model!F$3>=4,F9*Aannames!$B$11,0))*(1-Model!F$4)+Model!F$16 | G10: =(G9*$B$5+IF(Model!G$3>=4,G9*Aannames!$B$11,0))*(1-Model!G$4)+Model!G$16 | H10: =(H9*$B$5+IF(Model!H$3>=4,H9*Aannames!$B$11,0))*(1-Model!H$4)+Model!H$16 | I10: =(I9*$B$5+IF(Model!I$3>=4,I9*Aannames!$B$11,0))*(1-Model!I$4)+Model!I$16 | J10: =(J9*$B$5+IF(Model!J$3>=4,J9*Aannames!$B$11,0))*(1-Model!J$4)+Model!J$16 | ... N10: =(N9*$B$5+IF(Model!N$3>=4,N9*Aannames!$B$11,0))*(1-Model!N$4)+Model!N$16
A11: Totale kosten | C11: =Model!C$23-Model!C$21+Aannames!$B$14+C9*Aannames!$B$15 | D11: =Model!D$23-Model!D$21+Aannames!$B$14+D9*Aannames!$B$15 | E11: =Model!E$23-Model!E$21+Aannames!$B$14+E9*Aannames!$B$15 | F11: =Model!F$23-Model!F$21+Aannames!$B$14+F9*Aannames!$B$15 | G11: =Model!G$23-Model!G$21+Aannames!$B$14+G9*Aannames!$B$15 | H11: =Model!H$23-Model!H$21+Aannames!$B$14+H9*Aannames!$B$15 | I11: =Model!I$23-Model!I$21+Aannames!$B$14+I9*Aannames!$B$15 | J11: =Model!J$23-Model!J$21+Aannames!$B$14+J9*Aannames!$B$15 | ... N11: =Model!N$23-Model!N$21+Aannames!$B$14+N9*Aannames!$B$15
A12: Maandresultaat | C12: =C10-C11 | D12: =D10-D11 | E12: =E10-E11 | F12: =F10-F11 | G12: =G10-G11 | H12: =H10-H11 | I12: =I10-I11 | J12: =J10-J11 | ... N12: =N10-N11
A13: Kas zonder startkapitaal | C13: =C12 | D13: =C13+D12 | E13: =D13+E12 | F13: =E13+F12 | G13: =F13+G12 | H13: =G13+H12 | I13: =H13+I12 | J13: =I13+J12 | K13: =J13+K12 | ... N13: =M13+N12
A14: Positief? (1/0) | C14: =IF(C12>=0,1,0) | D14: =IF(D12>=0,1,0) | E14: =IF(E12>=0,1,0) | F14: =IF(F12>=0,1,0) | G14: =IF(G12>=0,1,0) | H14: =IF(H12>=0,1,0) | I14: =IF(I12>=0,1,0) | J14: =IF(J12>=0,1,0) | ... N14: =IF(N12>=0,1,0)
A16: Eerste break-even maand | B16: =IFERROR(MATCH(1,C14:N14,0),">12 maanden")
A17: Minimaal startkapitaal nodig (EUR) | B17: =MAX(0,-MIN(C13:N13))
A20: Scenario: Base
A21: Actieve opdrachtgevers | C21: =ROUND(Model!C$5/$C$4*IF(Model!C$3<=Aannames!$B$22,Aannames!$B$23,1),0)+Model!C$8 | D21: =C21+ROUND(Model!D$5/$C$4*IF(Model!D$3<=Aannames!$B$22,Aannames!$B$23,1),0)+Model!D$8-ROUND(C21*$C$3,0) | E21: =D21+ROUND(Model!E$5/$C$4*IF(Model!E$3<=Aannames!$B$22,Aannames!$B$23,1),0)+Model!E$8-ROUND(D21*$C$3,0) | F21: =E21+ROUND(Model!F$5/$C$4*IF(Model!F$3<=Aannames!$B$22,Aannames!$B$23,1),0)+Model!F$8-ROUND(E21*$C$3,0) | G21: =F21+ROUND(Model!G$5/$C$4*IF(Model!G$3<=Aannames!$B$22,Aannames!$B$23,1),0)+Model!G$8-ROUND(F21*$C$3,0) | H21: =G21+ROUND(Model!H$5/$C$4*IF(Model!H$3<=Aannames!$B$22,Aannames!$B$23,1),0)+Model!H$8-ROUND(G21*$C$3,0) | I21: =H21+ROUND(Model!I$5/$C$4*IF(Model!I$3<=Aannames!$B$22,Aannames!$B$23,1),0)+Model!I$8-ROUND(H21*$C$3,0) | J21: =I21+ROUND(Model!J$5/$C$4*IF(Model!J$3<=Aannames!$B$22,Aannames!$B$23,1),0)+Model!J$8-ROUND(I21*$C$3,0) | K21: =J21+ROUND(Model!K$5/$C$4*IF(Model!K$3<=Aannames!$B$22,Aannames!$B$23,1),0)+Model!K$8-ROUND(J21*$C$3,0) | ... N21: =M21+ROUND(Model!N$5/$C$4*IF(Model!N$3<=Aannames!$B$22,Aannames!$B$23,1),0)+Model!N$8-ROUND(M21*$C$3,0)
A22: Totale omzet | C22: =(C21*$C$5+IF(Model!C$3>=4,C21*Aannames!$B$11,0))*(1-Model!C$4)+Model!C$16 | D22: =(D21*$C$5+IF(Model!D$3>=4,D21*Aannames!$B$11,0))*(1-Model!D$4)+Model!D$16 | E22: =(E21*$C$5+IF(Model!E$3>=4,E21*Aannames!$B$11,0))*(1-Model!E$4)+Model!E$16 | F22: =(F21*$C$5+IF(Model!F$3>=4,F21*Aannames!$B$11,0))*(1-Model!F$4)+Model!F$16 | G22: =(G21*$C$5+IF(Model!G$3>=4,G21*Aannames!$B$11,0))*(1-Model!G$4)+Model!G$16 | H22: =(H21*$C$5+IF(Model!H$3>=4,H21*Aannames!$B$11,0))*(1-Model!H$4)+Model!H$16 | I22: =(I21*$C$5+IF(Model!I$3>=4,I21*Aannames!$B$11,0))*(1-Model!I$4)+Model!I$16 | J22: =(J21*$C$5+IF(Model!J$3>=4,J21*Aannames!$B$11,0))*(1-Model!J$4)+Model!J$16 | ... N22: =(N21*$C$5+IF(Model!N$3>=4,N21*Aannames!$B$11,0))*(1-Model!N$4)+Model!N$16
A23: Totale kosten | C23: =Model!C$23-Model!C$21+Aannames!$B$14+C21*Aannames!$B$15 | D23: =Model!D$23-Model!D$21+Aannames!$B$14+D21*Aannames!$B$15 | E23: =Model!E$23-Model!E$21+Aannames!$B$14+E21*Aannames!$B$15 | F23: =Model!F$23-Model!F$21+Aannames!$B$14+F21*Aannames!$B$15 | G23: =Model!G$23-Model!G$21+Aannames!$B$14+G21*Aannames!$B$15 | H23: =Model!H$23-Model!H$21+Aannames!$B$14+H21*Aannames!$B$15 | I23: =Model!I$23-Model!I$21+Aannames!$B$14+I21*Aannames!$B$15 | J23: =Model!J$23-Model!J$21+Aannames!$B$14+J21*Aannames!$B$15 | ... N23: =Model!N$23-Model!N$21+Aannames!$B$14+N21*Aannames!$B$15
A24: Maandresultaat | C24: =C22-C23 | D24: =D22-D23 | E24: =E22-E23 | F24: =F22-F23 | G24: =G22-G23 | H24: =H22-H23 | I24: =I22-I23 | J24: =J22-J23 | ... N24: =N22-N23
A25: Kas zonder startkapitaal | C25: =C24 | D25: =C25+D24 | E25: =D25+E24 | F25: =E25+F24 | G25: =F25+G24 | H25: =G25+H24 | I25: =H25+I24 | J25: =I25+J24 | K25: =J25+K24 | ... N25: =M25+N24
A26: Positief? (1/0) | C26: =IF(C24>=0,1,0) | D26: =IF(D24>=0,1,0) | E26: =IF(E24>=0,1,0) | F26: =IF(F24>=0,1,0) | G26: =IF(G24>=0,1,0) | H26: =IF(H24>=0,1,0) | I26: =IF(I24>=0,1,0) | J26: =IF(J24>=0,1,0) | ... N26: =IF(N24>=0,1,0)
A28: Eerste break-even maand | B28: =IFERROR(MATCH(1,C26:N26,0),">12 maanden")
A29: Minimaal startkapitaal nodig (EUR) | B29: =MAX(0,-MIN(C25:N25))
A32: Scenario: Optimistisch
A33: Actieve opdrachtgevers | C33: =ROUND(Model!C$5/$D$4*IF(Model!C$3<=Aannames!$B$22,Aannames!$B$23,1),0)+Model!C$8 | D33: =C33+ROUND(Model!D$5/$D$4*IF(Model!D$3<=Aannames!$B$22,Aannames!$B$23,1),0)+Model!D$8-ROUND(C33*$D$3,0) | E33: =D33+ROUND(Model!E$5/$D$4*IF(Model!E$3<=Aannames!$B$22,Aannames!$B$23,1),0)+Model!E$8-ROUND(D33*$D$3,0) | F33: =E33+ROUND(Model!F$5/$D$4*IF(Model!F$3<=Aannames!$B$22,Aannames!$B$23,1),0)+Model!F$8-ROUND(E33*$D$3,0) | G33: =F33+ROUND(Model!G$5/$D$4*IF(Model!G$3<=Aannames!$B$22,Aannames!$B$23,1),0)+Model!G$8-ROUND(F33*$D$3,0) | H33: =G33+ROUND(Model!H$5/$D$4*IF(Model!H$3<=Aannames!$B$22,Aannames!$B$23,1),0)+Model!H$8-ROUND(G33*$D$3,0) | I33: =H33+ROUND(Model!I$5/$D$4*IF(Model!I$3<=Aannames!$B$22,Aannames!$B$23,1),0)+Model!I$8-ROUND(H33*$D$3,0) | J33: =I33+ROUND(Model!J$5/$D$4*IF(Model!J$3<=Aannames!$B$22,Aannames!$B$23,1),0)+Model!J$8-ROUND(I33*$D$3,0) | K33: =J33+ROUND(Model!K$5/$D$4*IF(Model!K$3<=Aannames!$B$22,Aannames!$B$23,1),0)+Model!K$8-ROUND(J33*$D$3,0) | ... N33: =M33+ROUND(Model!N$5/$D$4*IF(Model!N$3<=Aannames!$B$22,Aannames!$B$23,1),0)+Model!N$8-ROUND(M33*$D$3,0)
A34: Totale omzet | C34: =(C33*$D$5+IF(Model!C$3>=4,C33*Aannames!$B$11,0))*(1-Model!C$4)+Model!C$16 | D34: =(D33*$D$5+IF(Model!D$3>=4,D33*Aannames!$B$11,0))*(1-Model!D$4)+Model!D$16 | E34: =(E33*$D$5+IF(Model!E$3>=4,E33*Aannames!$B$11,0))*(1-Model!E$4)+Model!E$16 | F34: =(F33*$D$5+IF(Model!F$3>=4,F33*Aannames!$B$11,0))*(1-Model!F$4)+Model!F$16 | G34: =(G33*$D$5+IF(Model!G$3>=4,G33*Aannames!$B$11,0))*(1-Model!G$4)+Model!G$16 | H34: =(H33*$D$5+IF(Model!H$3>=4,H33*Aannames!$B$11,0))*(1-Model!H$4)+Model!H$16 | I34: =(I33*$D$5+IF(Model!I$3>=4,I33*Aannames!$B$11,0))*(1-Model!I$4)+Model!I$16 | J34: =(J33*$D$5+IF(Model!J$3>=4,J33*Aannames!$B$11,0))*(1-Model!J$4)+Model!J$16 | ... N34: =(N33*$D$5+IF(Model!N$3>=4,N33*Aannames!$B$11,0))*(1-Model!N$4)+Model!N$16
A35: Totale kosten | C35: =Model!C$23-Model!C$21+Aannames!$B$14+C33*Aannames!$B$15 | D35: =Model!D$23-Model!D$21+Aannames!$B$14+D33*Aannames!$B$15 | E35: =Model!E$23-Model!E$21+Aannames!$B$14+E33*Aannames!$B$15 | F35: =Model!F$23-Model!F$21+Aannames!$B$14+F33*Aannames!$B$15 | G35: =Model!G$23-Model!G$21+Aannames!$B$14+G33*Aannames!$B$15 | H35: =Model!H$23-Model!H$21+Aannames!$B$14+H33*Aannames!$B$15 | I35: =Model!I$23-Model!I$21+Aannames!$B$14+I33*Aannames!$B$15 | J35: =Model!J$23-Model!J$21+Aannames!$B$14+J33*Aannames!$B$15 | ... N35: =Model!N$23-Model!N$21+Aannames!$B$14+N33*Aannames!$B$15
A36: Maandresultaat | C36: =C34-C35 | D36: =D34-D35 | E36: =E34-E35 | F36: =F34-F35 | G36: =G34-G35 | H36: =H34-H35 | I36: =I34-I35 | J36: =J34-J35 | ... N36: =N34-N35
A37: Kas zonder startkapitaal | C37: =C36 | D37: =C37+D36 | E37: =D37+E36 | F37: =E37+F36 | G37: =F37+G36 | H37: =G37+H36 | I37: =H37+I36 | J37: =I37+J36 | K37: =J37+K36 | ... N37: =M37+N36
A38: Positief? (1/0) | C38: =IF(C36>=0,1,0) | D38: =IF(D36>=0,1,0) | E38: =IF(E36>=0,1,0) | F38: =IF(F36>=0,1,0) | G38: =IF(G36>=0,1,0) | H38: =IF(H36>=0,1,0) | I38: =IF(I36>=0,1,0) | J38: =IF(J36>=0,1,0) | ... N38: =IF(N36>=0,1,0)
A40: Eerste break-even maand | B40: =IFERROR(MATCH(1,C38:N38,0),">12 maanden")
A41: Minimaal startkapitaal nodig (EUR) | B41: =MAX(0,-MIN(C37:N37))

Sheet Fasen
A1: Fasen & KPI's — model tegen het businessplan
A3: Fase | B3: Periode | C3: Doelen (businessplan) | D3: Break-even-criterium | E3: Model-prognose (base)
A4: Fase 1 – NL product-market fit | B4: Maand 0–6 | C4: Gratis beta (maand 1–3), daarna eerste betalende klanten; 10–25 opdrachtgevers | D4: Maandresultaat structureel >= 0 | E4: =Model!H18
A5: Fase 2 – verbreding + eerste export | B5: Maand 6–18 | C5: Abonnementen volledig, 100 opdrachtgevers, ~EUR 15k MRR-doel, UK (IR35) launch | D5: MRR >= totale kosten | E5: =Model!N18
A6: Fase 3 – platform & internationaal | B6: Maand 18–48 | C6: Rules-as-code engine, API/resellers, BE/DE/ES | D6: EBITDA-positief per markt | E6: buiten modelvenster
A8: KPI-doelen (maand 12)
A9: CAC (marketing) <= EUR 600 | B9: =Model!N28
A10: LTV / CAC >= 3 | B10: =Model!N30
A11: Maandelijkse churn <= 3% | B11: =Aannames!B7
A12: Omzet per maand (incl. ZZP + commissies) | B12: =Model!N18
A13: Minimaal startkapitaal (base) | B13: =Scenario!B29
A14: Minimaal startkapitaal (pessimistisch) | B14: =Scenario!B17
